{
	"name": "Arm",
	"plugin-id": "Sprite",
	"sid": 194114652191237,
	"isGlobal": false,
	"editorNewInstanceIsReplica": true,
	"instanceVariables": [],
	"behaviorTypes": [
		{
			"behaviorId": "Sin",
			"name": "Vertical",
			"sid": 671818418128868
		},
		{
			"behaviorId": "Sin",
			"name": "Horizontal",
			"sid": 524763206142678
		},
		{
			"behaviorId": "Sin",
			"name": "Bob",
			"sid": 868688882661121
		}
	],
	"effectTypes": [],
	"animations": {
		"items": [
			{
				"frames": [
					{
						"width": 320,
						"height": 180,
						"originX": 0,
						"originY": 0,
						"originalSource": "",
						"exportFormat": "lossless",
						"exportQuality": 0.8,
						"fileType": "image/png",
						"imageSpriteId": 5761915,
						"useCollisionPoly": true,
						"duration": 1,
						"tag": ""
					},
					{
						"width": 320,
						"height": 180,
						"originX": 0,
						"originY": 0,
						"originalSource": "",
						"exportFormat": "lossless",
						"exportQuality": 0.8,
						"fileType": "image/png",
						"imageSpriteId": 5746184,
						"useCollisionPoly": true,
						"duration": 1,
						"tag": ""
					},
					{
						"width": 320,
						"height": 180,
						"originX": 0,
						"originY": 0,
						"originalSource": "",
						"exportFormat": "lossless",
						"exportQuality": 0.8,
						"fileType": "image/png",
						"imageSpriteId": 3465093,
						"useCollisionPoly": true,
						"duration": 1,
						"tag": ""
					}
				],
				"sid": 936200843064003,
				"name": "Animation 1",
				"isLooping": false,
				"isPingPong": false,
				"repeatCount": 1,
				"repeatTo": 0,
				"speed": 5
			}
		],
		"subfolders": []
	}
}